cartographer_tuner/__init__.py
cartographer_tuner/cli/__init__.py
cartographer_tuner/cli/config_grid_search.py
cartographer_tuner/cli/lua_pgm_metrics.py
cartographer_tuner/cli/lua_to_pgm.py
cartographer_tuner/cli/pgm_corner_count.py
cartographer_tuner/cli/pgm_enclosed_areas.py
cartographer_tuner/cli/pgm_occupied_proportion.py
cartographer_tuner/config_optimizers/__init__.py
cartographer_tuner/config_optimizers/base_config_optimizer.py
cartographer_tuner/config_optimizers/exceptions.py
cartographer_tuner/config_optimizers/grid_search.py
cartographer_tuner/core/__init__.py
cartographer_tuner/core/cartographer_config_manager.py
cartographer_tuner/core/exceptions.py
cartographer_tuner/exceptions.py
cartographer_tuner/metrics/__init__.py
cartographer_tuner/metrics/calculators/__init__.py
cartographer_tuner/metrics/calculators/base_metric_calculator.py
cartographer_tuner/metrics/calculators/exceptions.py
cartographer_tuner/metrics/calculators/lua/__init__.py
cartographer_tuner/metrics/calculators/lua/base_lua_calculator.py
cartographer_tuner/metrics/calculators/lua/pgm_based_calculator.py
cartographer_tuner/metrics/calculators/pgm/__init__.py
cartographer_tuner/metrics/calculators/pgm/base_pgm_metric_calculator.py
cartographer_tuner/metrics/calculators/pgm/corner_count_calculator.py
cartographer_tuner/metrics/calculators/pgm/enclosed_areas_calculator.py
cartographer_tuner/metrics/calculators/pgm/occupied_proportion_calculator.py
cartographer_tuner/metrics/metric.py
cartographer_tuner/tools/__init__.py
cartographer_tuner/tools/combinations/__init__.py
cartographer_tuner/tools/combinations/lua_to_pgm.py
cartographer_tuner/tools/exceptions.py
cartographer_tuner/tools/ros/__init__.py
cartographer_tuner/tools/ros/base_ros_tool.py
cartographer_tuner/tools/ros/offline_cartographer_launcher.py
cartographer_tuner/tools/ros/pbstream_to_pgm_launcher.py
cartographer_tuner/utils/__init__.py
cartographer_tuner/utils/csv_stats_writer.py
cartographer_tuner/utils/terminal_runnable.py
cartographer_tuner-0.1.2.dist-info/LICENCE
cartographer_tuner-0.1.2.dist-info/METADATA
cartographer_tuner-0.1.2.dist-info/WHEEL
cartographer_tuner-0.1.2.dist-info/entry_points.txt
cartographer_tuner-0.1.2.dist-info/RECORD
