Metadata-Version: 2.3
Name: cartographer-tuner
Version: 0.1.2
Summary: A toolkit for Google-Cartographer tuning.
License: LICENCE
Keywords: cartographer,slam,mapping
Author: Vsevolod Vaskin
Requires-Python: >=3.10,<4.0
Classifier: License :: Other/Proprietary License
Classifier: Operating System :: POSIX :: Linux
Classifier: Programming Language :: Python :: 3
Classifier: Programming Language :: Python :: 3.10
Classifier: Programming Language :: Python :: 3.11
Classifier: Programming Language :: Python :: 3.12
Classifier: Programming Language :: Python :: 3.13
Requires-Dist: lark (>=1.2.2,<2.0.0)
Requires-Dist: lupa (>=2.4,<3.0)
Requires-Dist: open3d (>=0.19.0,<0.20.0)
Requires-Dist: opencv-python (>=4.11.0.86,<5.0.0.0)
Requires-Dist: pyyaml (>=6.0.2,<7.0.0)
